elasticdl_preprocessing/__init__.py
elasticdl_preprocessing/constants.py
elasticdl_preprocessing/requirements.txt
elasticdl_preprocessing/feature_column/__init__.py
elasticdl_preprocessing/feature_column/feature_column.py
elasticdl_preprocessing/layers/__init__.py
elasticdl_preprocessing/layers/concatenate_with_offset.py
elasticdl_preprocessing/layers/discretization.py
elasticdl_preprocessing/layers/hashing.py
elasticdl_preprocessing/layers/index_lookup.py
elasticdl_preprocessing/layers/log_round.py
elasticdl_preprocessing/layers/normalizer.py
elasticdl_preprocessing/layers/round_identity.py
elasticdl_preprocessing/layers/sparse_embedding.py
elasticdl_preprocessing/layers/to_number.py
elasticdl_preprocessing/layers/to_ragged.py
elasticdl_preprocessing/layers/to_sparse.py
elasticdl_preprocessing/utils/__init__.py
elasticdl_preprocessing/utils/analyzer_utils.py
elasticdl_preprocessing/utils/decorators.py
elasticdl_preprocessing-0.2.0rc3.dist-info/DESCRIPTION.rst
elasticdl_preprocessing-0.2.0rc3.dist-info/METADATA
elasticdl_preprocessing-0.2.0rc3.dist-info/RECORD
elasticdl_preprocessing-0.2.0rc3.dist-info/WHEEL
elasticdl_preprocessing-0.2.0rc3.dist-info/metadata.json
elasticdl_preprocessing-0.2.0rc3.dist-info/top_level.txt
